odoo9_addon_web_widget_float_formula-9.0.1.0.0-py2.7-nspkg.pth
odoo_addons/web_widget_float_formula/__openerp__.py
odoo_addons/web_widget_float_formula/__init__.py
odoo_addons/web_widget_float_formula/README.rst
odoo_addons/web_widget_float_formula/views/web_widget_float_formula.xml
odoo_addons/web_widget_float_formula/tests/test_js.py
odoo_addons/web_widget_float_formula/tests/__init__.py
odoo_addons/web_widget_float_formula/static/description/icon.png
odoo_addons/web_widget_float_formula/static/src/js/web_widget_float_formula.js
odoo_addons/web_widget_float_formula/static/tests/js/test_web_widget_float_formula.js
odoo9_addon_web_widget_float_formula-9.0.1.0.0.dist-info/top_level.txt
odoo9_addon_web_widget_float_formula-9.0.1.0.0.dist-info/WHEEL
odoo9_addon_web_widget_float_formula-9.0.1.0.0.dist-info/RECORD
odoo9_addon_web_widget_float_formula-9.0.1.0.0.dist-info/metadata.json
odoo9_addon_web_widget_float_formula-9.0.1.0.0.dist-info/DESCRIPTION.rst
odoo9_addon_web_widget_float_formula-9.0.1.0.0.dist-info/METADATA
odoo9_addon_web_widget_float_formula-9.0.1.0.0.dist-info/namespace_packages.txt
